zephyr/__init__.py
zephyr/cli.py
zephyr_ai-0.0.1.dist-info/METADATA
zephyr_ai-0.0.1.dist-info/WHEEL
zephyr_ai-0.0.1.dist-info/entry_points.txt
zephyr_ai-0.0.1.dist-info/top_level.txt
zephyr_ai-0.0.1.dist-info/RECORD
