Metadata-Version: 2.4
Name: zephyr-ai
Version: 0.0.1
Summary: Zephyr orchestration toolkit (namespace reservation stub)
Author-email: Your Org <dev@yourorg.com>
License: Proprietary
Project-URL: Homepage, https://github.com/your-org/zephyr-ai
Project-URL: Repository, https://github.com/your-org/zephyr-ai
Project-URL: Documentation, https://your-org.github.io/zephyr-ai
Project-URL: Issues, https://github.com/your-org/zephyr-ai/issues
Classifier: Programming Language :: Python :: 3
Classifier: Programming Language :: Python :: 3.9
Classifier: Development Status :: 3 - Alpha
Classifier: Intended Audience :: Developers
Classifier: Topic :: Software Development :: Build Tools
Requires-Python: >=3.9
